{
	"navigation": [
		{
			"title": "Home",
			"icon": "sap-icon://home",
			"expanded": true,
			"key": "home",
			"items": []
		},
		{
			"title": "Orders",
			"icon": "sap-icon://sales-order",
			"expanded": false,
			"key": "orders",
			"items": []
		},
		{
		  "title": "ProductData",
		  "icon": "sap-icon://product",
		  "expanded": false,
		  "key": "productData",
		  "items": []
		},
		{
			"title": "Settings",
			"icon": "sap-icon://settings",
			"expanded": false,
			"key": "masterSettings",
			"items": []
		},
		{
			"title": "Statistics",
			"icon": "sap-icon://Statistics",
			"expanded": true,
			"key": "statistics",
			"items": [
				{
					"title": "Usage Statistics",
					"key": "Usage Statistics was pressed"
				},
				{
					"title": "Order Statistics",
					"key": "orderStatistics"
				}
			]
		}
	],
	"fixedNavigation": [
		{
			"title": "Important Links",
			"icon": "sap-icon://chain-link",
			"key": "Important Links was pressed"
		},
		{
			"title": "Legal",
			"icon": "sap-icon://compare",
			"key": "Legal was pressed"
		}
	],
	"masterSettings": [
		{
			"title": "System Settings",
			"key": "systemSettings",
			"selected": true
		},
		{
			"title": "Order Settings",
			"key": "orderSettings",
			"selected": false
		},
		{
			"title": "Supplier Settings",
			"key": "supplierSettings",
			"selected": false
		},
		{
			"title": "Campaign Settings",
			"key": "campaignSettings",
			"selected": false
		},
		{
			"title": "Shipping Settings",
			"key": "shipping Settings",
			"selected": false
		}
	]
}